socks/__init__.py
socks/athena.py
socks/aws_lambda.py
socks/cloudwatch.py
socks/dynamodb.py
socks/s3.py
socks/secretsmanager.py
socks/sqs.py
socks/ssm.py
socks/sts.py
aws_socks-0.2.5.dist-info/WHEEL
aws_socks-0.2.5.dist-info/METADATA
aws_socks-0.2.5.dist-info/RECORD
