Metadata-Version: 2.1
Name: aws-socks
Version: 0.2.5
Summary: A wrapper for boto3 to provide one-liners for common AWS tasks.
Home-page: https://github.com/devenjarvis/aws-socks
License: MIT
Keywords: boto3,AWS
Author: Deven Jarvis
Author-email: devenjarvis@gmail.com
Requires-Python: >=3.6,<4.0
Classifier: Environment :: Console
Classifier: License :: OSI Approved :: MIT License
Classifier: Operating System :: OS Independent
Classifier: Programming Language :: Python :: 3
Classifier: Programming Language :: Python :: 3.6
Classifier: Programming Language :: Python :: 3.7
Classifier: Programming Language :: Python :: 3.8
Requires-Dist: boto3 (>=1.9,<2.0)
Project-URL: Repository, https://github.com/devenjarvis/aws-socks
